sighthound_api/__init__.py
sighthound_api-0.62.dist-info/LICENSE
sighthound_api-0.62.dist-info/METADATA
sighthound_api-0.62.dist-info/WHEEL
sighthound_api-0.62.dist-info/top_level.txt
sighthound_api-0.62.dist-info/RECORD
